apikey_auth/__init__.py
apikey_auth/admin.py
apikey_auth/api/__init__.py
apikey_auth/api/authentication/__init__.py
apikey_auth/api/authentication/apikey_authentication.py
apikey_auth/api/filters/__init__.py
apikey_auth/api/paginations/__init__.py
apikey_auth/api/paginations/limit_offset_pagination.py
apikey_auth/api/permissions/__init__.py
apikey_auth/api/permissions/api_key.py
apikey_auth/api/serializers/__init__.py
apikey_auth/api/serializers/api_key.py
apikey_auth/api/serializers/helper/get_serializer_cls.py
apikey_auth/api/serializers/user.py
apikey_auth/api/throttlings/__init__.py
apikey_auth/api/throttlings/role_base_throttle.py
apikey_auth/api/views/__init__.py
apikey_auth/api/views/api_key.py
apikey_auth/api/views/base.py
apikey_auth/apps.py
apikey_auth/constants/__init__.py
apikey_auth/constants/default_settings.py
apikey_auth/constants/types.py
apikey_auth/migrations/0001_initial.py
apikey_auth/migrations/__init__.py
apikey_auth/mixins/__init__.py
apikey_auth/mixins/admin/__init__.py
apikey_auth/mixins/admin/permission.py
apikey_auth/mixins/api/__init__.py
apikey_auth/mixins/api/config_api_attrs.py
apikey_auth/mixins/api/control_api_methods.py
apikey_auth/models.py
apikey_auth/settings/__init__.py
apikey_auth/settings/checks.py
apikey_auth/settings/conf.py
apikey_auth/templates/api_keys.html
apikey_auth/tests/__init__.py
apikey_auth/tests/admin/__init__.py
apikey_auth/tests/admin/test_api_key.py
apikey_auth/tests/api/__init__.py
apikey_auth/tests/api/authentication/__init__.py
apikey_auth/tests/api/authentication/test_apikey_auth.py
apikey_auth/tests/api/paginations/__init__.py
apikey_auth/tests/api/paginations/test_limit_offset_pagination.py
apikey_auth/tests/api/throttlings/__init__.py
apikey_auth/tests/api/throttlings/test_role_base_throttle.py
apikey_auth/tests/api/views/__init__.py
apikey_auth/tests/api/views/test_admin_apikey.py
apikey_auth/tests/api/views/test_apikey.py
apikey_auth/tests/api/views/test_base.py
apikey_auth/tests/conftest.py
dj_apikey_auth-1.0.0.dist-info/AUTHORS.md
dj_apikey_auth-1.0.0.dist-info/LICENSE
dj_apikey_auth-1.0.0.dist-info/METADATA
dj_apikey_auth-1.0.0.dist-info/WHEEL
dj_apikey_auth-1.0.0.dist-info/RECORD
